{
    "annotations": {
      "list": [
        {
          "builtIn": 1,
          "datasource": {
            "type": "grafana",
            "uid": "-- Grafana --"
          },
          "enable": true,
          "hide": true,
          "iconColor": "rgba(0, 211, 255, 1)",
          "name": "Annotations & Alerts",
          "type": "dashboard"
        }
      ]
    },
    "description": "크롤링 서버 (자동)",
    "editable": true,
    "fiscalYearStartMonth": 0,
    "graphTooltip": 0,
    "id": 7,
    "links": [],
    "panels": [
      {
        "datasource": {
          "type": "loki",
          "uid": "loki"
        },
        "gridPos": {
          "h": 7,
          "w": 24,
          "x": 0,
          "y": 0
        },
        "id": 1,
        "options": {
          "dedupStrategy": "none",
          "enableLogDetails": true,
          "prettifyLogMessage": false,
          "showCommonLabels": false,
          "showLabels": false,
          "showTime": false,
          "sortOrder": "Ascending",
          "wrapLogMessage": false
        },
        "targets": [
          {
            "datasource": {
              "type": "loki",
              "uid": "loki"
            },
            "editorMode": "builder",
            "expr": "{host=\"ip-10-0-11-208\"} |= ``",
            "queryType": "range",
            "refId": "A"
          }
        ],
        "title": "cra-server-1",
        "type": "logs"
      },
      {
        "datasource": {
          "type": "loki",
          "uid": "loki"
        },
        "gridPos": {
          "h": 7,
          "w": 24,
          "x": 0,
          "y": 7
        },
        "id": 2,
        "options": {
          "dedupStrategy": "none",
          "enableLogDetails": true,
          "prettifyLogMessage": false,
          "showCommonLabels": false,
          "showLabels": false,
          "showTime": false,
          "sortOrder": "Ascending",
          "wrapLogMessage": false
        },
        "targets": [
          {
            "datasource": {
              "type": "loki",
              "uid": "loki"
            },
            "editorMode": "builder",
            "expr": "{host=\"ip-10-0-11-87\"} |= ``",
            "queryType": "range",
            "refId": "A"
          }
        ],
        "title": "cra-server-2",
        "type": "logs"
      },
      {
        "datasource": {
          "type": "loki",
          "uid": "loki"
        },
        "gridPos": {
          "h": 7,
          "w": 24,
          "x": 0,
          "y": 14
        },
        "id": 3,
        "options": {
          "dedupStrategy": "none",
          "enableLogDetails": true,
          "prettifyLogMessage": false,
          "showCommonLabels": false,
          "showLabels": false,
          "showTime": false,
          "sortOrder": "Ascending",
          "wrapLogMessage": false
        },
        "targets": [
          {
            "datasource": {
              "type": "loki",
              "uid": "loki"
            },
            "editorMode": "builder",
            "expr": "{host=\"ip-10-0-11-66\"} |= ``",
            "queryType": "range",
            "refId": "A"
          }
        ],
        "title": "cra-server-3",
        "type": "logs"
      },
      {
        "datasource": {
          "type": "loki",
          "uid": "loki"
        },
        "gridPos": {
          "h": 7,
          "w": 24,
          "x": 0,
          "y": 21
        },
        "id": 4,
        "options": {
          "dedupStrategy": "none",
          "enableLogDetails": true,
          "prettifyLogMessage": false,
          "showCommonLabels": false,
          "showLabels": false,
          "showTime": false,
          "sortOrder": "Ascending",
          "wrapLogMessage": false
        },
        "targets": [
          {
            "datasource": {
              "type": "loki",
              "uid": "loki"
            },
            "editorMode": "builder",
            "expr": "{host=\"ip-10-0-11-47\"} |= ``",
            "queryType": "range",
            "refId": "A"
          }
        ],
        "title": "cra-server-4",
        "type": "logs"
      },
      {
        "datasource": {
          "type": "loki",
          "uid": "loki"
        },
        "gridPos": {
          "h": 6,
          "w": 24,
          "x": 0,
          "y": 28
        },
        "id": 5,
        "options": {
          "dedupStrategy": "none",
          "enableLogDetails": true,
          "prettifyLogMessage": false,
          "showCommonLabels": false,
          "showLabels": false,
          "showTime": false,
          "sortOrder": "Ascending",
          "wrapLogMessage": false
        },
        "targets": [
          {
            "datasource": {
              "type": "loki",
              "uid": "loki"
            },
            "editorMode": "builder",
            "expr": "{host=\"ip-10-0-11-26\"} |= ``",
            "queryType": "range",
            "refId": "A"
          }
        ],
        "title": "cra-server-5",
        "type": "logs"
      }
    ],
    "schemaVersion": 39,
    "tags": [],
    "templating": {
      "list": []
    },
    "time": {
      "from": "now-5m",
      "to": "now"
    },
    "timepicker": {},
    "timezone": "browser",
    "title": "👩‍💻 CRA (auto)",
    "uid": "bdvnyuco99yioc",
    "version": 6,
    "weekStart": ""
  }